termcolours/__about__.py
termcolours/__init__.py
termcolours/__main__.py
termcolours/cli.py
termcolours/assets/__init__.py
termcolours/assets/aga.ssv
termcolours/assets/ansi16.ssv
termcolours/assets/ansi16.txt
termcolours/assets/forest_vibes.ssv
termcolours/assets/gruvbox.ssv
termcolours/assets/gruvbox.txt
termcolours/assets/khaz.ssv
termcolours/assets/material_basic.ssv
termcolours/assets/material_basic.txt
termcolours/assets/matrix.ssv
termcolours/assets/navy_light_blue.ssv
termcolours/assets/nord.ssv
termcolours/assets/nord.txt
termcolours/assets/simple.ssv
termcolours/assets/solarized.ssv
termcolours/assets/solarized.txt
termcolours/assets/termcolors-basic-usage.png
termcolours/assets/termcolors-palette-mode.png
termcolours/assets/turquoise_depths.ssv
termcolours/lib/__init__.py
termcolours/lib/palette.py
termcolours/lib/m_utils/__init__.py
termcolours/lib/m_utils/auxiliary.py
termcolours/lib/m_utils/printing.py
termcolours/lib/softdev/__init__.py
termcolours/lib/softdev/debug.py
termcolours/lib/softdev/user_input.py
termcolours-0.11.3.dist-info/METADATA
termcolours-0.11.3.dist-info/WHEEL
termcolours-0.11.3.dist-info/entry_points.txt
termcolours-0.11.3.dist-info/licenses/LICENSE
termcolours-0.11.3.dist-info/RECORD
