Metadata-Version: 2.4
Name: termcolours
Version: 0.11.3
Summary: Interactive terminal color picker
Author: pykhaz
License: MIT
License-File: LICENSE
Requires-Python: >=3.10
Requires-Dist: pyperclip
